solists/__init__.py
solists/_node.py
solists/doubly_linked_list.py
solists/move_to_front_list.py
solists/transpose_list.py
solists-0.1.7.dist-info/LICENSE
solists-0.1.7.dist-info/WHEEL
solists-0.1.7.dist-info/METADATA
solists-0.1.7.dist-info/RECORD
