Metadata-Version: 2.1
Name: solists
Version: 0.1.7
Summary: Implementation of self-organizing lists.
Home-page: https://github.com/vsevolodbazhan/Sol
License: MIT
Author: Vsevolod Bazhan
Author-email: vsevozhan@yandex.ru
Requires-Python: >=3.7,<4.0
Classifier: License :: OSI Approved :: MIT License
Classifier: Programming Language :: Python :: 3
Classifier: Programming Language :: Python :: 3.7
Classifier: Programming Language :: Python :: 3.8
Project-URL: Repository, https://github.com/vsevolodbazhan/Sol
